vnpy_akshare/__init__.py
vnpy_akshare/akshare_datafeed.py
vnpy_akshare_cposture-1.0.3.dist-info/LICENSE
vnpy_akshare_cposture-1.0.3.dist-info/METADATA
vnpy_akshare_cposture-1.0.3.dist-info/WHEEL
vnpy_akshare_cposture-1.0.3.dist-info/top_level.txt
vnpy_akshare_cposture-1.0.3.dist-info/RECORD
